kb/__init__.py
kb/nl/__init__.py
kb/nl/api/__init__.py
kb/nl/api/oai.py
kb/nl/api/sru.py
kb/nl/collections/__init__.py
kb/nl/helpers/__init__.py
kb-0.1.8.dist-info/LICENSE.txt
kb-0.1.8.dist-info/METADATA
kb-0.1.8.dist-info/WHEEL
kb-0.1.8.dist-info/top_level.txt
kb-0.1.8.dist-info/RECORD
